executiveordermonitor/__init__.py
executiveordermonitor/__main__.py
executiveordermonitor/executiveordermonitor.py
executiveordermonitor-1.0.3.dist-info/LICENSE
executiveordermonitor-1.0.3.dist-info/METADATA
executiveordermonitor-1.0.3.dist-info/WHEEL
executiveordermonitor-1.0.3.dist-info/entry_points.txt
executiveordermonitor-1.0.3.dist-info/top_level.txt
executiveordermonitor-1.0.3.dist-info/RECORD
