Metadata-Version: 2.1
Name: executiveordermonitor
Version: 1.0.3
Summary: Monitor the Federal Register API for new Executive Orders
Author-email: Mihai Cosma <mcosma@gmail.com>
License: MIT License
Project-URL: Homepage, https://github.com/wakamex/executiveordermonitor
Project-URL: Bug Tracker, https://github.com/wakamex/executiveordermonitor/issues
Classifier: Programming Language :: Python :: 3
Classifier: License :: OSI Approved :: MIT License
Classifier: Operating System :: OS Independent
Requires-Python: >=3.8
License-File: LICENSE
Requires-Dist: requests >=2.32.3
